odoo/addons/stock_release_channel_shipment_advice_toursolver/README.rst
odoo/addons/stock_release_channel_shipment_advice_toursolver/__init__.py
odoo/addons/stock_release_channel_shipment_advice_toursolver/__manifest__.py
odoo/addons/stock_release_channel_shipment_advice_toursolver/i18n/it.po
odoo/addons/stock_release_channel_shipment_advice_toursolver/i18n/stock_release_channel_shipment_advice_toursolver.pot
odoo/addons/stock_release_channel_shipment_advice_toursolver/models/__init__.py
odoo/addons/stock_release_channel_shipment_advice_toursolver/models/shipment_advice.py
odoo/addons/stock_release_channel_shipment_advice_toursolver/models/stock_release_channel.py
odoo/addons/stock_release_channel_shipment_advice_toursolver/models/toursolver_task.py
odoo/addons/stock_release_channel_shipment_advice_toursolver/readme/CONTRIBUTORS.rst
odoo/addons/stock_release_channel_shipment_advice_toursolver/readme/DESCRIPTION.rst
odoo/addons/stock_release_channel_shipment_advice_toursolver/static/description/icon.png
odoo/addons/stock_release_channel_shipment_advice_toursolver/static/description/index.html
odoo/addons/stock_release_channel_shipment_advice_toursolver/tests/__init__.py
odoo/addons/stock_release_channel_shipment_advice_toursolver/tests/test_shipment_advice_planner_toursolver.py
odoo/addons/stock_release_channel_shipment_advice_toursolver/tests/cassettes/TestShipmentAdvicePlannerToursolver.test_plan_shipment_toursolver.yaml
odoo/addons/stock_release_channel_shipment_advice_toursolver/views/stock_release_channel.xml
odoo/addons/stock_release_channel_shipment_advice_toursolver/views/toursolver_task.xml
odoo/addons/stock_release_channel_shipment_advice_toursolver/wizards/__init__.py
odoo/addons/stock_release_channel_shipment_advice_toursolver/wizards/shipment_advice_planner.py
odoo_addon_stock_release_channel_shipment_advice_toursolver-16.0.1.1.0.2.dist-info/METADATA
odoo_addon_stock_release_channel_shipment_advice_toursolver-16.0.1.1.0.2.dist-info/WHEEL
odoo_addon_stock_release_channel_shipment_advice_toursolver-16.0.1.1.0.2.dist-info/top_level.txt
odoo_addon_stock_release_channel_shipment_advice_toursolver-16.0.1.1.0.2.dist-info/RECORD
