Metadata-Version: 2.1
Name: odoo-addon-stock_release_channel_shipment_advice_toursolver
Version: 16.0.1.1.0.2
Summary: Use TourSolver to plan shipment advices for ready and released pickings
Home-page: https://github.com/OCA/wms
Author: ACSONE SA/NV,Odoo Community Association (OCA)
Author-email: support@odoo-community.org
License: AGPL-3
Classifier: Programming Language :: Python
Classifier: Framework :: Odoo
Classifier: Framework :: Odoo :: 16.0
Classifier: License :: OSI Approved :: GNU Affero General Public License v3
Requires-Python: >=3.10
Requires-Dist: odoo-addon-shipment-advice-planner-toursolver<16.1dev,>=16.0dev
Requires-Dist: odoo-addon-stock-release-channel-shipment-advice<16.1dev,>=16.0dev
Requires-Dist: odoo<16.1dev,>=16.0a
